PyFlashToGPS.py
__init__.py
edge_finding_utilities.py
PyFlashToGPS-1.0.5.dist-info/METADATA
PyFlashToGPS-1.0.5.dist-info/WHEEL
PyFlashToGPS-1.0.5.dist-info/top_level.txt
PyFlashToGPS-1.0.5.dist-info/RECORD
