Metadata-Version: 2.1
Name: PyFlashToGPS
Version: 1.0.5
Summary: Processes flash-tagged SharpCap FITS recordings to insert GPS accurate timestamps
Author-email: "Robert L Anderson, Jr" <bob.anderson.ok@gmail.com>
License: MIT License
Project-URL: Repository, https://github.com/bob-anderson-ok/PyFlashToGPS
Keywords: flash,flash-tag,IOTAflash,SharpCap
